[{"game_pk": 716955, "home_name": "Chicago Cubs", "away_name": "Kansas City Royals", "home_pitcher": {"id": 592791, "fullName": "Jameson Taillon", "link": "/api/v1/people/592791"}, "away_pitcher": {"id": 666142, "fullName": "Cole Ragans", "link": "/api/v1/people/666142"}}, {"game_pk": 716956, "home_name": "Cleveland Guardians", "away_name": "Detroit Tigers", "home_pitcher": {"id": 668909, "fullName": "Gavin Williams", "link": "/api/v1/people/668909"}, "away_pitcher": {"id": 669373, "fullName": "Tarik Skubal", "link": "/api/v1/people/669373"}}, {"game_pk": 716959, "home_name": "Cleveland Guardians", "away_name": "Detroit Tigers", "home_pitcher": {"id": 675540, "fullName": "Xzavion Curry", "link": "/api/v1/people/675540"}, "away_pitcher": {"id": 666214, "fullName": "Joey Wentz", "link": "/api/v1/people/666214"}}, {"game_pk": 716954, "home_name": "Cincinnati Reds", "away_name": "Toronto Blue Jays", "home_pitcher": {"id": 664028, "fullName": "Brett Kennedy", "link": "/api/v1/people/664028"}, "away_pitcher": {"id": 621244, "fullName": "Jos\u00e9 Berr\u00edos", "link": "/api/v1/people/621244"}}, {"game_pk": 716960, "home_name": "Washington Nationals", "away_name": "Philadelphia Phillies", "home_pitcher": {"id": 672851, "fullName": "Joan Adon", "link": "/api/v1/people/672851"}, "away_pitcher": {"id": 547179, "fullName": "Michael Lorenzen", "link": "/api/v1/people/547179"}}, {"game_pk": 716953, "home_name": "New York Yankees", "away_name": "Boston Red Sox", "home_pitcher": {"id": 666745, "fullName": "Jhony Brito", "link": "/api/v1/people/666745"}, "away_pitcher": {"id": 678394, "fullName": "Brayan Bello", "link": "/api/v1/people/678394"}}, {"game_pk": 716949, "home_name": "Atlanta Braves", "away_name": "San Francisco Giants", "home_pitcher": {"id": 675911, "fullName": "Spencer Strider", "link": "/api/v1/people/675911"}, "away_pitcher": {"id": 502171, "fullName": "Alex Cobb", "link": "/api/v1/people/502171"}}, {"game_pk": 716950, "home_name": "Texas Rangers", "away_name": "Milwaukee Brewers", "home_pitcher": {"id": 571760, "fullName": "Andrew Heaney", "link": "/api/v1/people/571760"}, "away_pitcher": {"id": 605540, "fullName": "Brandon Woodruff", "link": "/api/v1/people/605540"}}, {"game_pk": 716948, "home_name": "Houston Astros", "away_name": "Seattle Mariners", "home_pitcher": {"id": 641585, "fullName": "J.P. France", "link": "/api/v1/people/641585"}, "away_pitcher": {"id": 682243, "fullName": "Bryce Miller", "link": "/api/v1/people/682243"}}, {"game_pk": 716951, "home_name": "Minnesota Twins", "away_name": "Pittsburgh Pirates", "home_pitcher": {"id": 641154, "fullName": "Pablo L\u00f3pez", "link": "/api/v1/people/641154"}, "away_pitcher": {"id": 656578, "fullName": "Andre Jackson", "link": "/api/v1/people/656578"}}, {"game_pk": 716952, "home_name": "St. Louis Cardinals", "away_name": "New York Mets", "home_pitcher": {"id": 668868, "fullName": "Zack Thompson", "link": "/api/v1/people/668868"}, "away_pitcher": {"id": 664192, "fullName": "Joey Lucchesi", "link": "/api/v1/people/664192"}}, {"game_pk": 716947, "home_name": "Colorado Rockies", "away_name": "Chicago White Sox", "home_pitcher": {"id": 663567, "fullName": "Peter Lambert", "link": "/api/v1/people/663567"}, "away_pitcher": {"id": 656629, "fullName": "Michael Kopech", "link": "/api/v1/people/656629"}}, {"game_pk": 716945, "home_name": "Los Angeles Angels", "away_name": "Tampa Bay Rays", "home_pitcher": {"id": 542881, "fullName": "Tyler Anderson", "link": "/api/v1/people/542881"}, "away_pitcher": {"id": 541640, "fullName": "Erasmo Ram\u00edrez", "link": "/api/v1/people/541640"}}, {"game_pk": 716944, "home_name": "Oakland Athletics", "away_name": "Baltimore Orioles", "home_pitcher": {"id": 660906, "fullName": "Francisco P\u00e9rez", "link": "/api/v1/people/660906"}, "away_pitcher": {"id": 502043, "fullName": "Kyle Gibson", "link": "/api/v1/people/502043"}}, {"game_pk": 716942, "home_name": "San Diego Padres", "away_name": "Arizona Diamondbacks", "home_pitcher": {"id": 607625, "fullName": "Seth Lugo", "link": "/api/v1/people/607625"}, "away_pitcher": {"id": 694297, "fullName": "Brandon Pfaadt", "link": "/api/v1/people/694297"}}, {"game_pk": 716946, "home_name": "Los Angeles Dodgers", "away_name": "Miami Marlins", "home_pitcher": {"id": 664062, "fullName": "Tony Gonsolin", "link": "/api/v1/people/664062"}, "away_pitcher": {"id": 645261, "fullName": "Sandy Alcantara", "link": "/api/v1/people/645261"}}]