[{"game_pk": 716438, "home_name": "Colorado Rockies", "away_name": "Los Angeles Dodgers", "home_pitcher": {"id": 502624, "fullName": "Chase Anderson", "link": "/api/v1/people/502624"}, "away_pitcher": {"id": 657571, "fullName": "Caleb Ferguson", "link": "/api/v1/people/657571"}}, {"game_pk": 716424, "home_name": "Colorado Rockies", "away_name": "Los Angeles Dodgers", "home_pitcher": {"id": 663372, "fullName": "Ryan Feltner", "link": "/api/v1/people/663372"}, "away_pitcher": {"id": 676272, "fullName": "Bobby Miller", "link": "/api/v1/people/676272"}}, {"game_pk": 716435, "home_name": "Cleveland Guardians", "away_name": "Cincinnati Reds", "home_pitcher": {"id": 608337, "fullName": "Lucas Giolito", "link": "/api/v1/people/608337"}, "away_pitcher": {"id": 668881, "fullName": "Hunter Greene", "link": "/api/v1/people/668881"}}, {"game_pk": 716434, "home_name": "Baltimore Orioles", "away_name": "Washington Nationals", "home_pitcher": {"id": 680694, "fullName": "Kyle Bradish", "link": "/api/v1/people/680694"}, "away_pitcher": {"id": 680686, "fullName": "Josiah Gray", "link": "/api/v1/people/680686"}}, {"game_pk": 716433, "home_name": "Detroit Tigers", "away_name": "Kansas City Royals", "home_pitcher": {"id": 681857, "fullName": "Reese Olson", "link": "/api/v1/people/681857"}, "away_pitcher": {"id": 425844, "fullName": "Zack Greinke", "link": "/api/v1/people/425844"}}, {"game_pk": 716432, "home_name": "Philadelphia Phillies", "away_name": "Pittsburgh Pirates", "home_pitcher": {"id": 605400, "fullName": "Aaron Nola", "link": "/api/v1/people/605400"}, "away_pitcher": {"id": 656605, "fullName": "Mitch Keller", "link": "/api/v1/people/656605"}}, {"game_pk": 716431, "home_name": "Toronto Blue Jays", "away_name": "New York Yankees", "home_pitcher": {"id": 592332, "fullName": "Kevin Gausman", "link": "/api/v1/people/592332"}, "away_pitcher": {"id": 650633, "fullName": "Michael King", "link": "/api/v1/people/650633"}}, {"game_pk": 716428, "home_name": "Boston Red Sox", "away_name": "Tampa Bay Rays", "home_pitcher": {"id": 656557, "fullName": "Tanner Houck", "link": "/api/v1/people/656557"}, "away_pitcher": {"id": 621107, "fullName": "Zach Eflin", "link": "/api/v1/people/621107"}}, {"game_pk": 716429, "home_name": "Atlanta Braves", "away_name": "Chicago Cubs", "home_pitcher": {"id": 693821, "fullName": "Bryce Elder", "link": "/api/v1/people/693821"}, "away_pitcher": {"id": 657006, "fullName": "Justin Steele", "link": "/api/v1/people/657006"}}, {"game_pk": 716421, "home_name": "Minnesota Twins", "away_name": "Oakland Athletics", "home_pitcher": {"id": 641927, "fullName": "Bailey Ober", "link": "/api/v1/people/641927"}, "away_pitcher": {"id": 621112, "fullName": "Paul Blackburn", "link": "/api/v1/people/621112"}}, {"game_pk": 716427, "home_name": "Chicago White Sox", "away_name": "Arizona Diamondbacks", "home_pitcher": {"id": 570632, "fullName": "Jos\u00e9 Ure\u00f1a", "link": "/api/v1/people/570632"}, "away_pitcher": {"id": 605200, "fullName": "Zach Davies", "link": "/api/v1/people/605200"}}, {"game_pk": 716423, "home_name": "Milwaukee Brewers", "away_name": "St. Louis Cardinals", "home_pitcher": {"id": 605288, "fullName": "Adrian Houser", "link": "/api/v1/people/605288"}, "away_pitcher": {"id": 571945, "fullName": "Miles Mikolas", "link": "/api/v1/people/571945"}}, {"game_pk": 716422, "home_name": "Los Angeles Angels", "away_name": "Texas Rangers", "home_pitcher": {"id": 672282, "fullName": "Reid Detmers", "link": "/api/v1/people/672282"}, "away_pitcher": {"id": 674003, "fullName": "Cody Bradford", "link": "/api/v1/people/674003"}}, {"game_pk": 716437, "home_name": "San Francisco Giants", "away_name": "San Diego Padres", "home_pitcher": {"id": 605154, "fullName": "John Brebbia", "link": "/api/v1/people/605154"}, "away_pitcher": {"id": 607625, "fullName": "Seth Lugo", "link": "/api/v1/people/607625"}}, {"game_pk": 716425, "home_name": "Seattle Mariners", "away_name": "Houston Astros", "home_pitcher": {"id": 669923, "fullName": "George Kirby", "link": "/api/v1/people/669923"}, "away_pitcher": {"id": 664299, "fullName": "Cristian Javier", "link": "/api/v1/people/664299"}}, {"game_pk": 716430, "home_name": "New York Mets", "away_name": "Miami Marlins", "home_pitcher": {"id": 664192, "fullName": "Joey Lucchesi", "link": "/api/v1/people/664192"}, "away_pitcher": {"id": 666129, "fullName": "Braxton Garrett", "link": "/api/v1/people/666129"}}]