[{"game_pk": 746630, "home_name": "Cleveland Guardians", "away_name": "Kansas City Royals", "home_pitcher": {"id": 663474, "fullName": "Triston McKenzie", "link": "/api/v1/people/663474"}, "away_pitcher": {"id": 607625, "fullName": "Seth Lugo", "link": "/api/v1/people/607625"}}, {"game_pk": 745497, "home_name": "Pittsburgh Pirates", "away_name": "Los Angeles Dodgers", "home_pitcher": {"id": 683003, "fullName": "Jared Jones", "link": "/api/v1/people/683003"}, "away_pitcher": {"id": 607192, "fullName": "Tyler Glasnow", "link": "/api/v1/people/607192"}}, {"game_pk": 746060, "home_name": "Miami Marlins", "away_name": "Tampa Bay Rays", "home_pitcher": {"id": 666200, "fullName": "Jes\u00fas Luzardo", "link": "/api/v1/people/666200"}, "away_pitcher": {"id": 686752, "fullName": "Ryan Pepiot", "link": "/api/v1/people/686752"}}, {"game_pk": 745568, "home_name": "Philadelphia Phillies", "away_name": "Milwaukee Brewers", "home_pitcher": {"id": 650911, "fullName": "Cristopher S\u00e1nchez", "link": "/api/v1/people/650911"}, "away_pitcher": {"id": 657649, "fullName": "Jared Koenig", "link": "/api/v1/people/657649"}}, {"game_pk": 744850, "home_name": "Washington Nationals", "away_name": "New York Mets", "home_pitcher": {"id": 687792, "fullName": "DJ Herz", "link": "/api/v1/people/687792"}, "away_pitcher": {"id": 656849, "fullName": "David Peterson", "link": "/api/v1/people/656849"}}, {"game_pk": 745739, "home_name": "New York Yankees", "away_name": "Minnesota Twins", "home_pitcher": {"id": 661563, "fullName": "Luis Gil", "link": "/api/v1/people/661563"}, "away_pitcher": {"id": 641927, "fullName": "Bailey Ober", "link": "/api/v1/people/641927"}}, {"game_pk": 744931, "home_name": "Toronto Blue Jays", "away_name": "Baltimore Orioles", "home_pitcher": {"id": 670950, "fullName": "Trevor Richards", "link": "/api/v1/people/670950"}, "away_pitcher": {"id": 669203, "fullName": "Corbin Burnes", "link": "/api/v1/people/669203"}}, {"game_pk": 746949, "home_name": "Boston Red Sox", "away_name": "Atlanta Braves", "home_pitcher": {"id": 676710, "fullName": "Kutter Crawford", "link": "/api/v1/people/676710"}, "away_pitcher": {"id": 608331, "fullName": "Max Fried", "link": "/api/v1/people/608331"}}, {"game_pk": 745010, "home_name": "Texas Rangers", "away_name": "Detroit Tigers", "home_pitcher": {"id": 641540, "fullName": "Dane Dunning", "link": "/api/v1/people/641540"}, "away_pitcher": {"id": 656427, "fullName": "Jack Flaherty", "link": "/api/v1/people/656427"}}, {"game_pk": 746872, "home_name": "Chicago Cubs", "away_name": "Chicago White Sox", "home_pitcher": {"id": 684007, "fullName": "Shota Imanaga", "link": "/api/v1/people/684007"}, "away_pitcher": {"id": 623167, "fullName": "Chris Flexen", "link": "/api/v1/people/623167"}}, {"game_pk": 746380, "home_name": "Houston Astros", "away_name": "St. Louis Cardinals", "home_pitcher": {"id": 681293, "fullName": "Spencer Arrighetti", "link": "/api/v1/people/681293"}, "away_pitcher": {"id": 669467, "fullName": "Andre Pallante", "link": "/api/v1/people/669467"}}, {"game_pk": 746550, "home_name": "Colorado Rockies", "away_name": "Cincinnati Reds", "home_pitcher": {"id": 621389, "fullName": "Ty Blach", "link": "/api/v1/people/621389"}, "away_pitcher": {"id": 593423, "fullName": "Frankie Montas", "link": "/api/v1/people/593423"}}, {"game_pk": 746222, "home_name": "Los Angeles Angels", "away_name": "San Diego Padres", "home_pitcher": {"id": 663776, "fullName": "Patrick Sandoval", "link": "/api/v1/people/663776"}, "away_pitcher": {"id": 800049, "fullName": "Adam Mazur", "link": "/api/v1/people/800049"}}, {"game_pk": 745656, "home_name": "Oakland Athletics", "away_name": "Seattle Mariners", "home_pitcher": {"id": 687765, "fullName": "Mitch Spence", "link": "/api/v1/people/687765"}, "away_pitcher": {"id": 669923, "fullName": "George Kirby", "link": "/api/v1/people/669923"}}, {"game_pk": 747196, "home_name": "Arizona Diamondbacks", "away_name": "San Francisco Giants", "home_pitcher": {"id": 686796, "fullName": "Blake Walston", "link": "/api/v1/people/686796"}, "away_pitcher": {"id": 690986, "fullName": "Kyle Harrison", "link": "/api/v1/people/690986"}}]