[{"date": "2022-04-07", "ip": 4.0, "er": 2}, {"date": "2022-04-12", "ip": 2.6666666666666665, "er": 6}, {"date": "2022-04-17", "ip": 5.333333333333333, "er": 2}, {"date": "2022-04-22", "ip": 1.6666666666666665, "er": 7}, {"date": "2022-04-28", "ip": 6.0, "er": 2}, {"date": "2022-05-04", "ip": 8.0, "er": 3}, {"date": "2022-05-10", "ip": 5.0, "er": 0}, {"date": "2022-05-15", "ip": 6.0, "er": 5}, {"date": "2022-05-21", "ip": 5.0, "er": 5}, {"date": "2022-05-26", "ip": 6.333333333333333, "er": 3}, {"date": "2022-05-31", "ip": 4.333333333333333, "er": 7}, {"date": "2022-06-05", "ip": 6.0, "er": 3}, {"date": "2022-06-11", "ip": 6.0, "er": 4}, {"date": "2022-06-16", "ip": 3.3333333333333335, "er": 2}, {"date": "2022-06-22", "ip": 4.0, "er": 3}, {"date": "2022-06-28", "ip": 8.0, "er": 1}, {"date": "2022-07-04", "ip": 7.0, "er": 1}, {"date": "2022-07-09", "ip": 6.0, "er": 4}, {"date": "2022-07-15", "ip": 5.0, "er": 5}, {"date": "2022-07-22", "ip": 5.0, "er": 5}, {"date": "2022-07-27", "ip": 0.6666666666666666, "er": 6}, {"date": "2022-08-01", "ip": 4.333333333333333, "er": 4}, {"date": "2022-08-06", "ip": 0.6666666666666666, "er": 6}, {"date": "2022-08-16", "ip": 6.0, "er": 4}, {"date": "2022-08-21", "ip": 5.333333333333333, "er": 2}, {"date": "2022-08-28", "ip": 6.0, "er": 1}, {"date": "2022-09-03", "ip": 7.0, "er": 1}, {"date": "2022-09-09", "ip": 6.666666666666667, "er": 5}, {"date": "2022-09-14", "ip": 6.0, "er": 1}, {"date": "2022-09-20", "ip": 0.6666666666666666, "er": 0}, {"date": "2022-10-02", "ip": 4.666666666666667, "er": 7}]