[{"game_pk": 776837, "home_name": "Washington Nationals", "away_name": "Athletics", "home_pitcher": {"id": 680730, "fullName": "Mitchell Parker", "link": "/api/v1/people/680730"}, "away_pitcher": {"id": 682052, "fullName": "Jacob Lopez", "link": "/api/v1/people/682052"}}, {"game_pk": 776830, "home_name": "Seattle Mariners", "away_name": "Chicago White Sox", "home_pitcher": {"id": 669302, "fullName": "Logan Gilbert", "link": "/api/v1/people/669302"}, "away_pitcher": {"id": 681343, "fullName": "Shane Smith", "link": "/api/v1/people/681343"}}, {"game_pk": 776840, "home_name": "Pittsburgh Pirates", "away_name": "Cincinnati Reds", "home_pitcher": {"id": 694973, "fullName": "Paul Skenes", "link": "/api/v1/people/694973"}, "away_pitcher": {"id": 663903, "fullName": "Brady Singer", "link": "/api/v1/people/663903"}}, {"game_pk": 776842, "home_name": "Atlanta Braves", "away_name": "Miami Marlins", "home_pitcher": {"id": 471911, "fullName": "Carlos Carrasco", "link": "/api/v1/people/471911"}, "away_pitcher": {"id": 691587, "fullName": "Eury P\u00e9rez", "link": "/api/v1/people/691587"}}]