[{"game_pk": 662299, "home_name": "Pittsburgh Pirates", "away_name": "Toronto Blue Jays", "home_pitcher": {"id": 664141, "fullName": "JT Brubaker", "link": "/api/v1/people/664141"}, "away_pitcher": {"id": 548389, "fullName": "Ross Stripling", "link": "/api/v1/people/548389"}}, {"game_pk": 663107, "home_name": "Cincinnati Reds", "away_name": "Colorado Rockies", "home_pitcher": {"id": 666157, "fullName": "Nick Lodolo", "link": "/api/v1/people/666157"}, "away_pitcher": {"id": 608566, "fullName": "Germ\u00e1n M\u00e1rquez", "link": "/api/v1/people/608566"}}, {"game_pk": 663108, "home_name": "Cincinnati Reds", "away_name": "Colorado Rockies", "home_pitcher": {"id": 502624, "fullName": "Chase Anderson", "link": "/api/v1/people/502624"}, "away_pitcher": {"id": 570632, "fullName": "Jos\u00e9 Ure\u00f1a", "link": "/api/v1/people/570632"}}, {"game_pk": 663354, "home_name": "Baltimore Orioles", "away_name": "Oakland Athletics", "home_pitcher": {"id": 657093, "fullName": "Spenser Watkins", "link": "/api/v1/people/657093"}, "away_pitcher": {"id": 661309, "fullName": "Adri\u00e1n Martinez", "link": "/api/v1/people/661309"}}, {"game_pk": 663213, "home_name": "Boston Red Sox", "away_name": "Texas Rangers", "home_pitcher": {"id": 677985, "fullName": "Jonathan Diaz", "link": "/api/v1/people/677985"}, "away_pitcher": {"id": 683227, "fullName": "Cody Freeman", "link": "/api/v1/people/683227"}}, {"game_pk": 661474, "home_name": "Atlanta Braves", "away_name": "Miami Marlins", "home_pitcher": {"id": 608331, "fullName": "Max Fried", "link": "/api/v1/people/608331"}, "away_pitcher": {"id": 641154, "fullName": "Pablo L\u00f3pez", "link": "/api/v1/people/641154"}}, {"game_pk": 662786, "home_name": "Detroit Tigers", "away_name": "Kansas City Royals", "home_pitcher": {"id": 666159, "fullName": "Matt Manning", "link": "/api/v1/people/666159"}, "away_pitcher": {"id": 666721, "fullName": "Max Castillo", "link": "/api/v1/people/666721"}}, {"game_pk": 662424, "home_name": "New York Mets", "away_name": "Washington Nationals", "home_pitcher": {"id": 471911, "fullName": "Carlos Carrasco", "link": "/api/v1/people/471911"}, "away_pitcher": {"id": 607200, "fullName": "Erick Fedde", "link": "/api/v1/people/607200"}}, {"game_pk": 661853, "home_name": "Tampa Bay Rays", "away_name": "New York Yankees", "home_pitcher": {"id": 542888, "fullName": "Shawn Armstrong", "link": "/api/v1/people/542888"}, "away_pitcher": {"id": 593423, "fullName": "Frankie Montas", "link": "/api/v1/people/593423"}}, {"game_pk": 661437, "home_name": "Chicago White Sox", "away_name": "Minnesota Twins", "home_pitcher": {"id": 608337, "fullName": "Lucas Giolito", "link": "/api/v1/people/608337"}, "away_pitcher": {"id": 605164, "fullName": "Dylan Bundy", "link": "/api/v1/people/605164"}}, {"game_pk": 661927, "home_name": "St. Louis Cardinals", "away_name": "Chicago Cubs", "home_pitcher": {"id": 571945, "fullName": "Miles Mikolas", "link": "/api/v1/people/571945"}, "away_pitcher": {"id": 573186, "fullName": "Marcus Stroman", "link": "/api/v1/people/573186"}}, {"game_pk": 662962, "home_name": "Cleveland Guardians", "away_name": "Seattle Mariners", "home_pitcher": {"id": 615698, "fullName": "Cal Quantrill", "link": "/api/v1/people/615698"}, "away_pitcher": {"id": 669923, "fullName": "George Kirby", "link": "/api/v1/people/669923"}}, {"game_pk": 662030, "home_name": "San Francisco Giants", "away_name": "Philadelphia Phillies", "home_pitcher": {"id": 607074, "fullName": "Carlos Rod\u00f3n", "link": "/api/v1/people/607074"}, "away_pitcher": {"id": 624133, "fullName": "Ranger Suarez", "link": "/api/v1/people/624133"}}, {"game_pk": 663435, "home_name": "Los Angeles Angels", "away_name": "Houston Astros", "home_pitcher": {"id": 656353, "fullName": "Tucker Davidson", "link": "/api/v1/people/656353"}, "away_pitcher": {"id": 664353, "fullName": "Jos\u00e9 Urquidy", "link": "/api/v1/people/664353"}}, {"game_pk": 663311, "home_name": "Arizona Diamondbacks", "away_name": "Milwaukee Brewers", "home_pitcher": {"id": 668678, "fullName": "Zac Gallen", "link": "/api/v1/people/668678"}, "away_pitcher": {"id": 669920, "fullName": "Jason Alexander", "link": "/api/v1/people/669920"}}, {"game_pk": 662599, "home_name": "Los Angeles Dodgers", "away_name": "San Diego Padres", "home_pitcher": {"id": 657571, "fullName": "Caleb Ferguson", "link": "/api/v1/people/657571"}, "away_pitcher": {"id": 605182, "fullName": "Mike Clevinger", "link": "/api/v1/people/605182"}}]