[{"game_pk": 717744, "home_name": "Chicago Cubs", "away_name": "Baltimore Orioles", "home_pitcher": {"id": 543294, "fullName": "Kyle Hendricks", "link": "/api/v1/people/543294"}, "away_pitcher": {"id": 608344, "fullName": "Cole Irvin", "link": "/api/v1/people/608344"}}, {"game_pk": 717749, "home_name": "Washington Nationals", "away_name": "Miami Marlins", "home_pitcher": {"id": 592866, "fullName": "Trevor Williams", "link": "/api/v1/people/592866"}, "away_pitcher": {"id": 645261, "fullName": "Sandy Alcantara", "link": "/api/v1/people/645261"}}, {"game_pk": 717743, "home_name": "New York Mets", "away_name": "St. Louis Cardinals", "home_pitcher": {"id": 656731, "fullName": "Tylor Megill", "link": "/api/v1/people/656731"}, "away_pitcher": {"id": 571945, "fullName": "Miles Mikolas", "link": "/api/v1/people/571945"}}, {"game_pk": 717742, "home_name": "Boston Red Sox", "away_name": "New York Yankees", "home_pitcher": {"id": 656557, "fullName": "Tanner Houck", "link": "/api/v1/people/656557"}, "away_pitcher": {"id": 593334, "fullName": "Domingo Germ\u00e1n", "link": "/api/v1/people/593334"}}, {"game_pk": 717745, "home_name": "Atlanta Braves", "away_name": "Colorado Rockies", "home_pitcher": {"id": 694363, "fullName": "Jared Shuster", "link": "/api/v1/people/694363"}, "away_pitcher": {"id": 659275, "fullName": "Dinelson Lamet", "link": "/api/v1/people/659275"}}, {"game_pk": 717741, "home_name": "Texas Rangers", "away_name": "Toronto Blue Jays", "home_pitcher": {"id": 527048, "fullName": "Mart\u00edn P\u00e9rez", "link": "/api/v1/people/527048"}, "away_pitcher": {"id": 592332, "fullName": "Kevin Gausman", "link": "/api/v1/people/592332"}}, {"game_pk": 717737, "home_name": "Houston Astros", "away_name": "Cincinnati Reds", "home_pitcher": {"id": 641585, "fullName": "J.P. France", "link": "/api/v1/people/641585"}, "away_pitcher": {"id": 671096, "fullName": "Andrew Abbott", "link": "/api/v1/people/671096"}}, {"game_pk": 717736, "home_name": "Kansas City Royals", "away_name": "Los Angeles Angels", "home_pitcher": {"id": 663903, "fullName": "Brady Singer", "link": "/api/v1/people/663903"}, "away_pitcher": {"id": 663776, "fullName": "Patrick Sandoval", "link": "/api/v1/people/663776"}}, {"game_pk": 717738, "home_name": "Minnesota Twins", "away_name": "Detroit Tigers", "home_pitcher": {"id": 657746, "fullName": "Joe Ryan", "link": "/api/v1/people/657746"}, "away_pitcher": {"id": 676684, "fullName": "Will Vest", "link": "/api/v1/people/676684"}}, {"game_pk": 717740, "home_name": "Milwaukee Brewers", "away_name": "Pittsburgh Pirates", "home_pitcher": {"id": 527054, "fullName": "Julio Teheran", "link": "/api/v1/people/527054"}, "away_pitcher": {"id": 448179, "fullName": "Rich Hill", "link": "/api/v1/people/448179"}}, {"game_pk": 717739, "home_name": "Arizona Diamondbacks", "away_name": "Cleveland Guardians", "home_pitcher": {"id": 668678, "fullName": "Zac Gallen", "link": "/api/v1/people/668678"}, "away_pitcher": {"id": 657053, "fullName": "Touki Toussaint", "link": "/api/v1/people/657053"}}, {"game_pk": 717732, "home_name": "San Diego Padres", "away_name": "Tampa Bay Rays", "home_pitcher": {"id": 506433, "fullName": "Yu Darvish", "link": "/api/v1/people/506433"}, "away_pitcher": {"id": 663556, "fullName": "Shane McClanahan", "link": "/api/v1/people/663556"}}, {"game_pk": 717735, "home_name": "Oakland Athletics", "away_name": "Philadelphia Phillies", "home_pitcher": {"id": 676664, "fullName": "JP Sears", "link": "/api/v1/people/676664"}, "away_pitcher": {"id": 592836, "fullName": "Taijuan Walker", "link": "/api/v1/people/592836"}}, {"game_pk": 717731, "home_name": "Los Angeles Dodgers", "away_name": "San Francisco Giants", "home_pitcher": {"id": 686218, "fullName": "Emmet Sheehan", "link": "/api/v1/people/686218"}, "away_pitcher": {"id": 605154, "fullName": "John Brebbia", "link": "/api/v1/people/605154"}}, {"game_pk": 717733, "home_name": "Seattle Mariners", "away_name": "Chicago White Sox", "home_pitcher": {"id": 693433, "fullName": "Bryan Woo", "link": "/api/v1/people/693433"}, "away_pitcher": {"id": 656629, "fullName": "Michael Kopech", "link": "/api/v1/people/656629"}}]