[{"game_pk": 745155, "home_name": "St. Louis Cardinals", "away_name": "Kansas City Royals", "home_pitcher": {"id": 669467, "fullName": "Andre Pallante", "link": "/api/v1/people/669467"}, "away_pitcher": {"id": 679525, "fullName": "Alec Marsh", "link": "/api/v1/people/679525"}}, {"game_pk": 745156, "home_name": "St. Louis Cardinals", "away_name": "Kansas City Royals", "home_pitcher": {"id": 700669, "fullName": "Gordon Graceffo", "link": "/api/v1/people/700669"}, "away_pitcher": {"id": 608379, "fullName": "Michael Wacha", "link": "/api/v1/people/608379"}}, {"game_pk": 746772, "home_name": "Chicago White Sox", "away_name": "Minnesota Twins", "home_pitcher": {"id": 607200, "fullName": "Erick Fedde", "link": "/api/v1/people/607200"}, "away_pitcher": {"id": 641927, "fullName": "Bailey Ober", "link": "/api/v1/people/641927"}}, {"game_pk": 746773, "home_name": "Chicago White Sox", "away_name": "Minnesota Twins", "home_pitcher": {"id": 689672, "fullName": "Drew Thorpe", "link": "/api/v1/people/689672"}, "away_pitcher": {"id": 641154, "fullName": "Pablo L\u00f3pez", "link": "/api/v1/people/641154"}}, {"game_pk": 747015, "home_name": "Baltimore Orioles", "away_name": "Chicago Cubs", "home_pitcher": {"id": 669203, "fullName": "Corbin Burnes", "link": "/api/v1/people/669203"}, "away_pitcher": {"id": 684007, "fullName": "Shota Imanaga", "link": "/api/v1/people/684007"}}, {"game_pk": 746453, "home_name": "Detroit Tigers", "away_name": "Cleveland Guardians", "home_pitcher": {"id": 681857, "fullName": "Reese Olson", "link": "/api/v1/people/681857"}, "away_pitcher": {"id": 676440, "fullName": "Tanner Bibee", "link": "/api/v1/people/676440"}}, {"game_pk": 745394, "home_name": "San Diego Padres", "away_name": "Seattle Mariners", "home_pitcher": {"id": 650633, "fullName": "Michael King", "link": "/api/v1/people/650633"}, "away_pitcher": {"id": 682243, "fullName": "Bryce Miller", "link": "/api/v1/people/682243"}}, {"game_pk": 745069, "home_name": "Tampa Bay Rays", "away_name": "New York Yankees", "home_pitcher": {"id": 621107, "fullName": "Zach Eflin", "link": "/api/v1/people/621107"}, "away_pitcher": {"id": 573186, "fullName": "Marcus Stroman", "link": "/api/v1/people/573186"}}, {"game_pk": 745556, "home_name": "Philadelphia Phillies", "away_name": "Los Angeles Dodgers", "home_pitcher": {"id": 650911, "fullName": "Cristopher S\u00e1nchez", "link": "/api/v1/people/650911"}, "away_pitcher": {"id": 694813, "fullName": "Gavin Stone", "link": "/api/v1/people/694813"}}, {"game_pk": 746689, "home_name": "Cincinnati Reds", "away_name": "Colorado Rockies", "home_pitcher": {"id": 593423, "fullName": "Frankie Montas", "link": "/api/v1/people/593423"}, "away_pitcher": {"id": 607536, "fullName": "Kyle Freeland", "link": "/api/v1/people/607536"}}, {"game_pk": 745796, "home_name": "New York Mets", "away_name": "Washington Nationals", "home_pitcher": {"id": 622663, "fullName": "Luis Severino", "link": "/api/v1/people/622663"}, "away_pitcher": {"id": 571578, "fullName": "Patrick Corbin", "link": "/api/v1/people/571578"}}, {"game_pk": 746934, "home_name": "Boston Red Sox", "away_name": "Oakland Athletics", "home_pitcher": {"id": 601713, "fullName": "Nick Pivetta", "link": "/api/v1/people/601713"}, "away_pitcher": {"id": 676664, "fullName": "JP Sears", "link": "/api/v1/people/676664"}}, {"game_pk": 746366, "home_name": "Houston Astros", "away_name": "Miami Marlins", "home_pitcher": {"id": 664285, "fullName": "Framber Valdez", "link": "/api/v1/people/664285"}, "away_pitcher": {"id": 663773, "fullName": "Bryan Hoeing", "link": "/api/v1/people/663773"}}, {"game_pk": 745969, "home_name": "Milwaukee Brewers", "away_name": "Pittsburgh Pirates", "home_pitcher": {"id": 668964, "fullName": "Tobias Myers", "link": "/api/v1/people/668964"}, "away_pitcher": {"id": 527048, "fullName": "Mart\u00edn P\u00e9rez", "link": "/api/v1/people/527048"}}, {"game_pk": 746205, "home_name": "Los Angeles Angels", "away_name": "Texas Rangers", "home_pitcher": {"id": 656288, "fullName": "Griffin Canning", "link": "/api/v1/people/656288"}, "away_pitcher": {"id": 547179, "fullName": "Michael Lorenzen", "link": "/api/v1/people/547179"}}, {"game_pk": 747179, "home_name": "Arizona Diamondbacks", "away_name": "Atlanta Braves", "home_pitcher": {"id": 677944, "fullName": "Slade Cecconi", "link": "/api/v1/people/677944"}, "away_pitcher": {"id": 450203, "fullName": "Charlie Morton", "link": "/api/v1/people/450203"}}, {"game_pk": 745318, "home_name": "San Francisco Giants", "away_name": "Toronto Blue Jays", "home_pitcher": {"id": 657277, "fullName": "Logan Webb", "link": "/api/v1/people/657277"}, "away_pitcher": {"id": 605135, "fullName": "Chris Bassitt", "link": "/api/v1/people/605135"}}]